prodsensor/__init__.py
prodsensor/__main__.py
prodsensor/cli.py
prodsensor/client.py
prodsensor/formatters.py
prodsensor_cli-1.0.1.dist-info/METADATA
prodsensor_cli-1.0.1.dist-info/WHEEL
prodsensor_cli-1.0.1.dist-info/entry_points.txt
prodsensor_cli-1.0.1.dist-info/RECORD
