Metadata-Version: 2.4
Name: prodsensor-cli
Version: 1.0.1
Summary: CLI tool for ProdSensor production readiness analysis
Project-URL: Homepage, https://prodsensor.com
Project-URL: Documentation, https://prodsensor.com/docs/cli
Project-URL: Repository, https://github.com/prodsensor/prodsensor-cli
Author-email: ProdSensor <support@prodsensor.com>
License-Expression: MIT
Keywords: ci-cd,code-analysis,devops,production-readiness
Classifier: Development Status :: 4 - Beta
Classifier: Environment :: Console
Classifier: Intended Audience :: Developers
Classifier: License :: OSI Approved :: MIT License
Classifier: Operating System :: OS Independent
Classifier: Programming Language :: Python :: 3
Classifier: Programming Language :: Python :: 3.9
Classifier: Programming Language :: Python :: 3.10
Classifier: Programming Language :: Python :: 3.11
Classifier: Programming Language :: Python :: 3.12
Classifier: Topic :: Software Development :: Quality Assurance
Classifier: Topic :: Software Development :: Testing
Requires-Python: >=3.9
Requires-Dist: click>=8.0.0
Requires-Dist: httpx>=0.24.0
Requires-Dist: pydantic>=2.0.0
Requires-Dist: rich>=13.0.0
Provides-Extra: dev
Requires-Dist: pytest-asyncio>=0.21.0; extra == 'dev'
Requires-Dist: pytest>=7.0.0; extra == 'dev'
Requires-Dist: respx>=0.20.0; extra == 'dev'
